designer_dna/__init__.py
designer_dna/_oligonucleotides.cp314-win_arm64.pyd
designer_dna/_oligonucleotides.pyi
designer_dna/_oligonucleotides.pyx
designer_dna/_oligos.cp314-win_arm64.pyd
designer_dna/_oligos.pxd
designer_dna/_oligos.pyi
designer_dna/_oligos.pyx
designer_dna/oligos.py
designer_dna/headers/common.pxd
designer_dna/headers/narray.pxd
designer_dna/headers/numeric_array.hpp
designer_dna/headers/oligos.h
designer_dna-0.0.1.dist-info/licenses/LICENSE
designer_dna-0.0.1.dist-info/METADATA
designer_dna-0.0.1.dist-info/WHEEL
designer_dna-0.0.1.dist-info/top_level.txt
designer_dna-0.0.1.dist-info/RECORD
