Metadata-Version: 2.4
Name: designer_dna
Version: 0.0.1
Summary: Project description here.
Author-email: Jason C Del Rio <spillthetea917@gmail.com>
Maintainer-email: Jason C Del Rio <spillthetea917@gmail.com>
License: BSD 3-Clause License
Project-URL: homepage, https://github.com/Spill-Tea/DesignerDNA
Project-URL: issues, https://github.com/Spill-Tea/DesignerDNA/issues
Keywords: DNA,design,ligation,optimization
Classifier: Programming Language :: Python :: 3
Classifier: Intended Audience :: Science/Research
Classifier: Topic :: Scientific/Engineering
Classifier: Topic :: Scientific/Engineering :: Bio-Informatics
Requires-Python: >=3.11
License-File: LICENSE
Provides-Extra: dev
Requires-Dist: designer_dna[commit,doc,lint,test,type]; extra == "dev"
Requires-Dist: tox; extra == "dev"
Provides-Extra: commit
Requires-Dist: pre-commit; extra == "commit"
Provides-Extra: doc
Requires-Dist: sphinx; extra == "doc"
Requires-Dist: furo; extra == "doc"
Requires-Dist: sphinx_multiversion; extra == "doc"
Provides-Extra: test
Requires-Dist: pytest; extra == "test"
Requires-Dist: coverage; extra == "test"
Requires-Dist: pytest-xdist; extra == "test"
Provides-Extra: lint
Requires-Dist: pylint; extra == "lint"
Requires-Dist: ruff; extra == "lint"
Provides-Extra: type
Requires-Dist: mypy; extra == "type"
Dynamic: license-file
